mebularts/__init__.py
mebularts/fake_data.py
mebularts-0.1.5.dist-info/LICENSE
mebularts-0.1.5.dist-info/METADATA
mebularts-0.1.5.dist-info/WHEEL
mebularts-0.1.5.dist-info/top_level.txt
mebularts-0.1.5.dist-info/RECORD
